unpacker/__init__.py
unpacker/py.typed
unpacker/cli/__init__.py
unpacker/cli/entry_point.py
unpacker/main/__init__.py
unpacker/main/main.py
unpacker/models/__init__.py
unpacker/models/path.py
unpacker-0.1.1.dist-info/LICENSE
unpacker-0.1.1.dist-info/METADATA
unpacker-0.1.1.dist-info/WHEEL
unpacker-0.1.1.dist-info/entry_points.txt
unpacker-0.1.1.dist-info/top_level.txt
unpacker-0.1.1.dist-info/RECORD
