Metadata-Version: 2.1
Name: unpacker
Version: 0.1.1
Summary: Clean up and unpack items in working directory
Author-email: Quinten Roets <qdr2104@columbia.edu>
License: MIT
Project-URL: Source Code, https://github.com/quintenroets/unpacker
Requires-Python: >=3.10
License-File: LICENSE
Requires-Dist: package-utils <1,>=0.6.1
Requires-Dist: powercli <1,>=0.2.0
Requires-Dist: superpathlib <3,>=2.0.2
Provides-Extra: dev
Requires-Dist: hypothesis <7,>=6.97.1 ; extra == 'dev'
Requires-Dist: package-dev-tools <1,>=0.5.11 ; extra == 'dev'
Requires-Dist: package-dev-utils <1,>=0.1.6 ; extra == 'dev'
